Workbook

Sheet Export Summary
B3: This document was exported from Numbers. Each table was converted to an Excel worksheet. All other objects on each Numbers sheet were placed on separate worksheets. Please be aware that formula calculations may differ in Excel.
B7: Numbers Sheet Name | C7: Numbers Table Name | D7: Excel Worksheet Name
B9: Raw Data
C10: Table 1 | D10: Raw Data
B11: Dashboard
C12: Table 1 | D12: Dashboard
B13: Pivot Analysis
C14: Table 1 | D14: Pivot Analysis
B15: Regression
C16: Table 1 | D16: Regression
B17: Insights
C18: Table 1 | D18: Insights

Sheet Raw Data
A1: Financial Year | B1: Revenue (₹ Cr) | C1: Net Profit (₹ Cr) | D1: Operating Cash Flow (₹ Cr) | E1: Revenue Growth % | F1: Profit Margin % | G1: OCF Margin %
A2: FY2016-17 | B2: 108646 | C2: 26751 | D2: 24464 | F2: {=C2/B2} -> 0.24622167 | G2: {=D2/B2} -> 0.22517166
A3: FY2017-18 | B3: 123104 | C3: 25075 | D3: 27890 | E3: {=(B3-B2)/B2} -> 0.13307439 | F3: {=C3/B3} -> 0.20368956 | G3: {=D3/B3} -> 0.22655641
A4: FY2018-19 | B4: 146463 | C4: 31472 | D4: 32649 | E4: {=(B4-B3)/B3} -> 0.18975013 | F4: {=C4/B4} -> 0.21488021 | G4: {=D4/B4} -> 0.22291637
A5: FY2019-20 | B5: 156949 | C5: 32340 | D5: 33588 | E5: {=(B5-B4)/B4} -> 0.071594874 | F5: {=C5/B5} -> 0.2060542 | G5: {=D5/B5} -> 0.21400582
A6: FY2020-21 | B6: 164177 | C6: 32430 | D6: 41035 | E6: {=(B6-B5)/B5} -> 0.046053177 | F6: {=C6/B6} -> 0.19753071 | G6: {=D6/B6} -> 0.24994366
A7: FY2021-22 | B7: 191754 | C7: 38327 | D7: 39889 | E7: {=(B7-B6)/B6} -> 0.16797115 | F7: {=C7/B7} -> 0.19987588 | G7: {=D7/B7} -> 0.20802174
A8: FY2022-23 | B8: 225458 | C8: 42303 | D8: 44963 | E8: {=(B8-B7)/B7} -> 0.17576687 | F8: {=C8/B8} -> 0.1876314 | G8: {=D8/B8} -> 0.19942961
A9: FY2023-24 | B9: 240893 | C9: 46585 | D9: 49099 | E9: {=(B9-B8)/B8} -> 0.068460645 | F9: {=C9/B9} -> 0.19338461 | G9: {=D9/B9} -> 0.20382078
A10: FY2024-25 | B10: 255324 | C10: 48553 | D10: 48908 | E10: {=(B10-B9)/B9} -> 0.059906265 | F10: {=C10/B10} -> 0.1901623 | G10: {=D10/B10} -> 0.19155269
A11: FY2025-26 | B11: 267021 | C11: 49210 | D11: 52094 | E11: {=(B11-B10)/B10} -> 0.04581238 | F11: {=C11/B11} -> 0.18429262 | G11: {=D11/B11} -> 0.19509327

Sheet Dashboard
A1: TCS FINANCIAL ANALYSIS DASHBOARD
A4: Revenue Growth % | E4: Profit Margin % | I4: Operating Cash Flow
A5: {='Raw Data'!E11} -> 0.04581238 | E5: {='Raw Data'!F11} -> 0.18429262 | I5: {='Raw Data'!D11} -> 52094

Sheet Pivot Analysis
A1: PIVOT ANALYSIS
A3: Metric | B3: Value | D3: Financial Year
A4: Revenue (₹ Cr) | B4: {=INDEX('Raw Data'!$B$2:$B$11,MATCH($D$4,'Raw Data'!$A$2:$A$11,0))} -> 267021 | D4: FY2025-26
A5: Net Profit (₹ Cr) | B5: {=INDEX('Raw Data'!$C$2:$C$11,MATCH($D$4,'Raw Data'!$A$2:$A$11,0))} -> 49210
A6: Operating Cash Flow (₹ Cr) | B6: {=INDEX('Raw Data'!$D$2:$D$11,MATCH($D$4,'Raw Data'!$A$2:$A$11,0))} -> 52094 | D6: Select a financial year to view its metrics.
A7: Revenue Growth % | B7: {=INDEX('Raw Data'!$E$2:$E$11,MATCH($D$4,'Raw Data'!$A$2:$A$11,0))} -> 0.04581238
A8: Profit Margin % | B8: {=INDEX('Raw Data'!$F$2:$F$11,MATCH($D$4,'Raw Data'!$A$2:$A$11,0))} -> 0.18429262
A9: OCF Margin % | B9: {=INDEX('Raw Data'!$G$2:$G$11,MATCH($D$4,'Raw Data'!$A$2:$A$11,0))} -> 0.19509327

Sheet Regression
A1: LINEAR REGRESSION — REVENUE
A3: Year Index | B3: Financial Year | C3: Actual Revenue | D3: Predicted Revenue | E3: Residual | G3: Metric | H3: Value
A4: 1 | B4: {='Raw Data'!A2} -> FY2016-17 | C4: {='Raw Data'!B2} -> 108646 | D4: {=SLOPE($C$4:$C$13,$A$4:$A$13)*A4+INTERCEPT($C$4:$C$13,$A$4:$A$13)} -> 104628.84 | E4: {=C4-D4} -> 4017.1636 | G4: Slope | H4: {=SLOPE(C4:C13,A4:A13)} -> 18522.236
A5: 2 | B5: {='Raw Data'!A3} -> FY2017-18 | C5: {='Raw Data'!B3} -> 123104 | D5: {=SLOPE($C$4:$C$13,$A$4:$A$13)*A5+INTERCEPT($C$4:$C$13,$A$4:$A$13)} -> 123151.07 | E5: {=C5-D5} -> -47.072727 | G5: Intercept | H5: {=INTERCEPT(C4:C13,A4:A13)} -> 86106.6
A6: 3 | B6: {='Raw Data'!A4} -> FY2018-19 | C6: {='Raw Data'!B4} -> 146463 | D6: {=SLOPE($C$4:$C$13,$A$4:$A$13)*A6+INTERCEPT($C$4:$C$13,$A$4:$A$13)} -> 141673.31 | E6: {=C6-D6} -> 4789.6909 | G6: FY2026-27 Revenue Prediction | H6: {=H4*11+H5} -> 289851.2
A7: 4 | B7: {='Raw Data'!A5} -> FY2019-20 | C7: {='Raw Data'!B5} -> 156949 | D7: {=SLOPE($C$4:$C$13,$A$4:$A$13)*A7+INTERCEPT($C$4:$C$13,$A$4:$A$13)} -> 160195.55 | E7: {=C7-D7} -> -3246.5455 | G7: R² | H7: 0.98422219
A8: 5 | B8: {='Raw Data'!A6} -> FY2020-21 | C8: {='Raw Data'!B6} -> 164177 | D8: {=SLOPE($C$4:$C$13,$A$4:$A$13)*A8+INTERCEPT($C$4:$C$13,$A$4:$A$13)} -> 178717.78 | E8: {=C8-D8} -> -14540.782
A9: 6 | B9: {='Raw Data'!A7} -> FY2021-22 | C9: {='Raw Data'!B7} -> 191754 | D9: {=SLOPE($C$4:$C$13,$A$4:$A$13)*A9+INTERCEPT($C$4:$C$13,$A$4:$A$13)} -> 197240.02 | E9: {=C9-D9} -> -5486.0182
A10: 7 | B10: {='Raw Data'!A8} -> FY2022-23 | C10: {='Raw Data'!B8} -> 225458 | D10: {=SLOPE($C$4:$C$13,$A$4:$A$13)*A10+INTERCEPT($C$4:$C$13,$A$4:$A$13)} -> 215762.25 | E10: {=C10-D10} -> 9695.7455
A11: 8 | B11: {='Raw Data'!A9} -> FY2023-24 | C11: {='Raw Data'!B9} -> 240893 | D11: {=SLOPE($C$4:$C$13,$A$4:$A$13)*A11+INTERCEPT($C$4:$C$13,$A$4:$A$13)} -> 234284.49 | E11: {=C11-D11} -> 6608.5091
A12: 9 | B12: {='Raw Data'!A10} -> FY2024-25 | C12: {='Raw Data'!B10} -> 255324 | D12: {=SLOPE($C$4:$C$13,$A$4:$A$13)*A12+INTERCEPT($C$4:$C$13,$A$4:$A$13)} -> 252806.73 | E12: {=C12-D12} -> 2517.2727
A13: 10 | B13: {='Raw Data'!A11} -> FY2025-26 | C13: {='Raw Data'!B11} -> 267021 | D13: {=SLOPE($C$4:$C$13,$A$4:$A$13)*A13+INTERCEPT($C$4:$C$13,$A$4:$A$13)} -> 271328.96 | E13: {=C13-D13} -> -4307.9636
A15: Method | B15: Linear regression using Excel SLOPE, INTERCEPT and RSQ formulas.

Sheet Insights
A1: INSIGHTS & INTERPRETATION
A3: Observation | B3: Interpretation
A4: Revenue trend | B4: Revenue increases across the supplied FY2016-17 to FY2025-26 data, with positive year-on-year growth in the periods shown.
A5: Profitability | B5: Net profit and profit margin are positive throughout the supplied dataset and the margin remains in the same general range across the period.
A6: Cash flow | B6: Operating cash flow increases over the supplied period, indicating higher operating cash generation in the later years of the dataset.
A7: Regression prediction | B7: The linear regression model provides a FY2026-27 revenue estimate based on the historical year-index trend. R² indicates how much of the historical variation is explained by that linear relationship.
